README
setup.py
vortaro/__init__.py
vortaro/__main__.py
vortaro/highlight.py
vortaro/models.py
vortaro/transliterate.py
vortaro/ui.py
vortaro.egg-info/PKG-INFO
vortaro.egg-info/SOURCES.txt
vortaro.egg-info/dependency_links.txt
vortaro.egg-info/entry_points.txt
vortaro.egg-info/requires.txt
vortaro.egg-info/top_level.txt
vortaro/formats/__init__.py
vortaro/formats/cedict.py
vortaro/formats/dictcc.py
vortaro/formats/espdic.py
vortaro/formats/http.py
vortaro/test/__init__.py
vortaro/test/test_highlight.py
vortaro/test/test_transliterate.py