Metadata-Version: 1.1
Name: vortaro
Version: 1.0.0
Summary: Query bilingual dictionaries.
Home-page: https://thomaslevine.com/scm/vortaro/
Author: Thomas Levine
Author-email: _@thomaslevine.com
License: AGPL
Platform: UNKNOWN
Classifier: Programming Language :: Python :: 3.6
